{
  "generated_at": "2026-05-17T19:42:59.713151+00:00",
  "week_ending": "17/05/2026",
  "ig": {
    "followers": 657,
    "media_count": 1224,
    "posts_this_week": 15,
    "total_likes": 20,
    "total_comments": 1,
    "avg_likes_per_post": 1.3,
    "engagement_rate": 0.0021,
    "top_posts": [
      {
        "caption": "✨ רגע, איפה בדיוק אנחנו נמצאים?!  מבט כלפי מעלה על כיפה מעוטרת בזהב, שכבות של קשתות ואלפי נקודות אור",
        "likes": 3,
        "comments": 1,
        "date": "2026-05-13"
      },
      {
        "caption": "📸 מגדל פיזה השיפוע  קווים מובילים ופרספקטיבה: הצלם צילם מזווית נמוכה מאוד — כמעט מהקרקע — כך שכל קוו",
        "likes": 3,
        "comments": 0,
        "date": "2026-05-13"
      },
      {
        "caption": "הגעתי לגנים הבהאיים בחיפה עם הזריחה, לפני שהשערים נפתחו לציבור — ואלו היו דקות של קסם טהור. הקווים ה",
        "likes": 2,
        "comments": 0,
        "date": "2026-05-16"
      },
      {
        "caption": "⁨\tצילמתי את הפרפר הכחול הזה — *Polyommatus icarus* — בטכניקת מאקרו (צילום תקריב קיצוני של נושאים זעי",
        "likes": 2,
        "comments": 0,
        "date": "2026-05-15"
      },
      {
        "caption": "צילום מאקרו של שפירית אדומה-לוהטת (Trithemis arteriosa או מין דומה), נחה על קצה מוט מתכת בלוי, על רק",
        "likes": 2,
        "comments": 0,
        "date": "2026-05-13"
      }
    ],
    "best_post": {
      "caption": "✨ רגע, איפה בדיוק אנחנו נמצאים?!\n\nמבט כלפי מעלה על כיפה מעוטרת בזהב, שכבות של קשתות ואלפי נקודות אור — זה נראה כמו מקום ",
      "likes": 3,
      "date": "2026-05-13"
    }
  },
  "fb": {
    "fans": 136,
    "posts_this_week": 0,
    "total_likes": 0,
    "total_comments": 0,
    "avg_likes_per_post": 0,
    "engagement_rate": 0,
    "top_posts": [],
    "best_post": {
      "message": "",
      "likes": 0,
      "date": ""
    }
  },
  "fb_pages": [
    {
      "label": "erezphoto",
      "name": "amit erez photos",
      "page_id": "339707206917",
      "fans": 136,
      "posts_this_week": 0,
      "total_likes": 0,
      "total_comments": 0,
      "avg_likes_per_post": 0,
      "engagement_rate": 0,
      "top_posts": [],
      "best_post": {
        "message": "",
        "likes": 0,
        "date": ""
      }
    },
    {
      "label": "erezfamily",
      "name": "erezfamily",
      "page_id": "669524179579160",
      "fans": 0,
      "posts_this_week": 0,
      "total_likes": 0,
      "total_comments": 0,
      "avg_likes_per_post": 0,
      "engagement_rate": 0,
      "top_posts": [],
      "best_post": {
        "message": "",
        "likes": 0,
        "date": ""
      }
    }
  ],
  "prev": {
    "ig_followers": 657,
    "ig_posts_this_week": 15,
    "ig_total_likes": 21,
    "fb_fans": 135,
    "fb_posts_this_week": 0,
    "fb_total_likes": 0
  },
  "recommendations": [
    "פרסם פחות פוסטים אבל באיכות גבוהה יותר - השבוע 15 פוסטים הניבו רק 20 לייקים, נסה 5-7 פוסטים עם תוכן מעובד יותר",
    "הפוסט הטוב ביותר שלך היה תמונת אדריכלות עם כיתוב סיפורי ומעורר סקרנות - המשך בסגנון זה של שאלות ותיאורים חווייתיים בכל פוסט",
    "הפעל את עמוד הפייסבוק amit erez photos שיש לו 136 עוקבים על ידי שיתוף לפחות 3 פוסטים מאינסטגרם השבוע - זה קהל קיים שאינו מקבל תוכן",
    "הוסף לפחות 5 האשטאגים ממוקדים לכל פוסט כגון photography_israel או ישראל_צילום כדי להגדיל חשיפה אורגנית מעבר ל-657 העוקבים הקיימים"
  ]
}